MANIFEST.in
README.rst
REQUIREMENTS.txt
setup.py
Microbe.egg-info/PKG-INFO
Microbe.egg-info/SOURCES.txt
Microbe.egg-info/dependency_links.txt
Microbe.egg-info/entry_points.txt
Microbe.egg-info/requires.txt
Microbe.egg-info/top_level.txt
microbe/__init__.py
microbe/admin.py
microbe/babel.cfg
microbe/commands.py
microbe/markdown_content.py
microbe/messages.pot
microbe/settings.py
microbe/utils.py
microbe/views.py
microbe/flatcontent/__init__.py
microbe/flatcontent/forms.py
microbe/flatcontent/models.py
microbe/mods/__init__.py
microbe/mods/auth/__init__.py
microbe/mods/auth/forms.py
microbe/mods/auth/views.py
microbe/mods/comments/__init__.py
microbe/mods/comments/views.py
microbe/mods/config/__init__.py
microbe/mods/config/forms.py
microbe/mods/config/views.py
microbe/mods/contents/__init__.py
microbe/mods/contents/views.py
microbe/mods/links/__init__.py
microbe/mods/links/forms.py
microbe/mods/links/models.py
microbe/mods/links/views.py
microbe/mods/media/__init__.py
microbe/mods/media/models.py
microbe/mods/media/views.py
microbe/mods/search/__init__.py
microbe/mods/search/forms.py
microbe/mods/themes/__init__.py
microbe/mods/themes/views.py
microbe/mods/users/__init__.py
microbe/mods/users/forms.py
microbe/mods/users/models.py
microbe/mods/users/views.py
microbe/static/css/admin_style.css
microbe/static/css/foundation-icons.css
microbe/static/css/foundation-icons.eot
microbe/static/css/foundation-icons.svg
microbe/static/css/foundation-icons.ttf
microbe/static/css/foundation-icons.woff
microbe/static/css/foundation.min.css
microbe/static/css/normalize.css
microbe/static/css/svgs/fi-address-book.svg
microbe/static/css/svgs/fi-alert.svg
microbe/static/css/svgs/fi-align-center.svg
microbe/static/css/svgs/fi-align-justify.svg
microbe/static/css/svgs/fi-align-left.svg
microbe/static/css/svgs/fi-align-right.svg
microbe/static/css/svgs/fi-anchor.svg
microbe/static/css/svgs/fi-annotate.svg
microbe/static/css/svgs/fi-archive.svg
microbe/static/css/svgs/fi-arrow-down.svg
microbe/static/css/svgs/fi-arrow-left.svg
microbe/static/css/svgs/fi-arrow-right.svg
microbe/static/css/svgs/fi-arrow-up.svg
microbe/static/css/svgs/fi-arrows-compress.svg
